dotGraph/__init__.py
dotGraph-0.0.1.dist-info/LICENSE
dotGraph-0.0.1.dist-info/METADATA
dotGraph-0.0.1.dist-info/WHEEL
dotGraph-0.0.1.dist-info/top_level.txt
dotGraph-0.0.1.dist-info/RECORD
